pi_web_sdk/__init__.py
pi_web_sdk/client.py
pi_web_sdk/config.py
pi_web_sdk/event_hierarchy.py
pi_web_sdk/exceptions.py
pi_web_sdk/controllers/__init__.py
pi_web_sdk/controllers/analysis.py
pi_web_sdk/controllers/asset.py
pi_web_sdk/controllers/attribute.py
pi_web_sdk/controllers/attribute_trait.py
pi_web_sdk/controllers/base.py
pi_web_sdk/controllers/batch.py
pi_web_sdk/controllers/data.py
pi_web_sdk/controllers/enumeration.py
pi_web_sdk/controllers/event.py
pi_web_sdk/controllers/metrics.py
pi_web_sdk/controllers/notification.py
pi_web_sdk/controllers/omf.py
pi_web_sdk/controllers/security.py
pi_web_sdk/controllers/stream.py
pi_web_sdk/controllers/system.py
pi_web_sdk/controllers/table.py
pi_web_sdk/controllers/time_rule.py
pi_web_sdk/controllers/unit.py
pi_web_sdk/models/__init__.py
pi_web_sdk/models/analysis.py
pi_web_sdk/models/asset.py
pi_web_sdk/models/attribute.py
pi_web_sdk/models/base.py
pi_web_sdk/models/batch.py
pi_web_sdk/models/data.py
pi_web_sdk/models/enumeration.py
pi_web_sdk/models/event.py
pi_web_sdk/models/notification.py
pi_web_sdk/models/omf.py
pi_web_sdk/models/responses.py
pi_web_sdk/models/security.py
pi_web_sdk/models/stream.py
pi_web_sdk/models/table.py
pi_web_sdk/models/time_rule.py
pi_web_sdk/models/unit.py
pi_web_sdk-0.1.34.dist-info/METADATA
pi_web_sdk-0.1.34.dist-info/WHEEL
pi_web_sdk-0.1.34.dist-info/top_level.txt
pi_web_sdk-0.1.34.dist-info/RECORD
