Metadata-Version: 2.4
Name: pi-web-sdk
Version: 0.1.34
Summary: Python client SDK for the AVEVA PI Web API with typed controllers and request helpers
Author: PI Web API SDK Maintainers
License: Proprietary
Project-URL: Homepage, https://example.com/pi-web-sdk
Project-URL: Repository, https://example.com/pi-web-sdk/source
Keywords: osi,pi,web,api,sdk
Classifier: Development Status :: 3 - Alpha
Classifier: Intended Audience :: Developers
Classifier: License :: Other/Proprietary License
Classifier: Programming Language :: Python
Classifier: Programming Language :: Python :: 3
Classifier: Programming Language :: Python :: 3.9
Classifier: Programming Language :: Python :: 3.10
Classifier: Programming Language :: Python :: 3.11
Classifier: Programming Language :: Python :: 3.12
Classifier: Topic :: Software Development :: Libraries :: Python Modules
Requires-Python: >=3.9
Requires-Dist: requests<3,>=2.31
Requires-Dist: urllib3<3,>=2.0
